dt4dds/__init__.py
dt4dds/properties.py
dt4dds/analysis/__init__.py
dt4dds/analysis/alignment.py
dt4dds/analysis/analysis.py
dt4dds/analysis/config.py
dt4dds/analysis/dataaggregation.py
dt4dds/analysis/errormapper.py
dt4dds/analysis/fileio.py
dt4dds/analysis/mapping.py
dt4dds/analysis/phix.fasta
dt4dds/bin/analysis.py
dt4dds/bin/scenario.py
dt4dds/bin/utils.py
dt4dds/bin/analysis-configs/breakage.yaml
dt4dds/bin/analysis-configs/photolithographic.yaml
dt4dds/bin/analysis-configs/standard.yaml
dt4dds/bin/scenario-configs/best-case.py
dt4dds/bin/scenario-configs/breakage-aging.py
dt4dds/bin/scenario-configs/density-benchmark.py
dt4dds/bin/scenario-configs/density-storage.py
dt4dds/bin/scenario-configs/longterm-storage.py
dt4dds/bin/scenario-configs/photolithographic-synthesis.py
dt4dds/bin/scenario-configs/worst-case.py
dt4dds/datastructures/__init__.py
dt4dds/datastructures/seq.py
dt4dds/datastructures/seqpool.py
dt4dds/helpers/__init__.py
dt4dds/helpers/config.py
dt4dds/helpers/errorgenerator.py
dt4dds/helpers/generators.py
dt4dds/helpers/logging.py
dt4dds/helpers/step.py
dt4dds/helpers/tools.py
dt4dds/processes/__init__.py
dt4dds/processes/aging.py
dt4dds/processes/array_synthesis.py
dt4dds/processes/dilution.py
dt4dds/processes/pcr.py
dt4dds/processes/preparation.py
dt4dds/processes/purification.py
dt4dds/processes/sbs_sequencing.py
dt4dds/settings/__init__.py
dt4dds/settings/aging.yaml
dt4dds/settings/array_synthesis_customarray.yaml
dt4dds/settings/array_synthesis_customarray_GCall.yaml
dt4dds/settings/array_synthesis_customarray_GCfix.yaml
dt4dds/settings/array_synthesis_photolithographic.yaml
dt4dds/settings/array_synthesis_twist.yaml
dt4dds/settings/defaults.py
dt4dds/settings/fixed_aging.yaml
dt4dds/settings/iseq100.yaml
dt4dds/settings/pcr_Q5.yaml
dt4dds/settings/pcr_exo.yaml
dt4dds/settings/pcr_hifi.yaml
dt4dds/settings/pcr_taq.yaml
dt4dds/settings/properties.yaml
dt4dds/settings/settings.py
dt4dds-1.1.0.dist-info/LICENSE
dt4dds-1.1.0.dist-info/METADATA
dt4dds-1.1.0.dist-info/WHEEL
dt4dds-1.1.0.dist-info/entry_points.txt
dt4dds-1.1.0.dist-info/top_level.txt
dt4dds-1.1.0.dist-info/RECORD
