Metadata-Version: 2.1
Name: dt4dds
Version: 1.1.0
Summary: dt4dds is a Python package providing a customizable, digital representation of the widely-used DNA data storage workflow involving array synthesis, PCR, Aging, and Sequencing-By-Synthesis. By modelling each part of such user-defined workflows with fully customizable experimental parameters, dt4dds enables data-driven experimental design and rational design of redundancy. dt4dds also includes a pipeline for comprehensively analyzing errors in sequencing data, both from experiments and si
Author-email: Andreas Gimpel <andreas.gimpel@chem.ethz.ch>
License: GNU GENERAL PUBLIC LICENSE
Project-URL: Homepage, https://dt4dds.ethz.ch
Project-URL: Repository, https://github.com/fml-ethz/dt4dds
Classifier: Development Status :: 5 - Production/Stable
Classifier: Programming Language :: Python
Classifier: Topic :: Scientific/Engineering :: Bio-Informatics
Requires-Python: >=3.8
License-File: LICENSE
Requires-Dist: numpy
Requires-Dist: scipy
Requires-Dist: pandas
Requires-Dist: biopython
Requires-Dist: edlib
Requires-Dist: numba
Requires-Dist: plotly
Requires-Dist: PyYAML
Requires-Dist: rapidfuzz
Requires-Dist: ruamel.yaml
Requires-Dist: tqdm
Requires-Dist: rich
Requires-Dist: configargparse
Requires-Dist: pysam
Requires-Dist: seqfold
